[
  {
    "id": 0,
    "translated": "Alright, just like before, I've picked out some scenes that I personally want to talk about, so let's take a look at them together."
  },
  {
    "id": 1,
    "translated": "Here they are."
  },
  {
    "id": 2,
    "translated": "."
  },
  {
    "id": 3,
    "translated": "."
  },
  {
    "id": 4,
    "translated": "It's so good."
  },
  {
    "id": 5,
    "translated": "It's just really good."
  },
  {
    "id": 6,
    "translated": "That's what I think."
  },
  {
    "id": 7,
    "translated": "Since I've already chosen my own career path, seeing the moment someone else makes their choice,"
  },
  {
    "id": 8,
    "translated": "even if it's just through an event story, it makes me feel like..."
  },
  {
    "id": 9,
    "translated": "well, there are definitely moments where you wonder if you're doing the right thing."
  },
  {
    "id": 10,
    "translated": "I'm sure everyone has those moments."
  },
  {
    "id": 11,
    "translated": "But if you can look back in 10 or 20 years"
  },
  {
    "id": 12,
    "translated": "and think, \"I'm glad I made that choice back then,\""
  },
  {
    "id": 13,
    "translated": "then I think that's a great thing. And I believe effort is what makes that possible."
  },
  {
    "id": 14,
    "translated": "When it comes to things that require effort, I don't think there's such a thing as a \"wrong\" choice."
  },
  {
    "id": 15,
    "translated": "If you put in the effort, you might still have moments a year or two later"
  },
  {
    "id": 16,
    "translated": "where you think, \"Maybe I shouldn't have done this.\""
  },
  {
    "id": 17,
    "translated": "But looking back after 10 or 20 years, I'm sure there are times where it all connects in the end."
  },
  {
    "id": 18,
    "translated": "You'll think, \"If I hadn't done that then, I wouldn't be able to do this now.\""
  },
  {
    "id": 19,
    "translated": "Even in different jobs, I'm sure people feel that. For those currently working hard,"
  },
  {
    "id": 20,
    "translated": "or those who want to find something to work hard at, I hope this event story can be a catalyst for you to make that decision."
  },
  {
    "id": 21,
    "translated": "With that said, I'd like to talk about the illustrations now."
  },
  {
    "id": 22,
    "translated": "Let me read a message."
  },
  {
    "id": 23,
    "translated": "This one is from Meshi-san. Thank you very much."
  },
  {
    "id": 24,
    "translated": "Thank you."
  },
  {
    "id": 25,
    "translated": "\"Hello, Sato-san.\""
  },
  {
    "id": 26,
    "translated": "\"I'm always having fun playing ProSeka.\""
  },
  {
    "id": 27,
    "translated": "\"The 4-star illustrations this time, especially Mizuki's, were so good that I went all out on the gacha\""
  },
  {
    "id": 28,
    "translated": "\"to make sure I got them.\""
  },
  {
    "id": 29,
    "translated": "\"Just like in Secret Distance or the light music club song, Michi wa... Izuko?\""
  },
  {
    "id": 30,
    "translated": "\"Izuko.\""
  },
  {
    "id": 31,
    "translated": "\"...it's an illustration of Mizuki in a space with torsos.\" Torsos appear quite often in Mizuki's illustrations."
  },
  {
    "id": 32,
    "translated": "Not mannequins, but the ones for clothes, like this."
  },
  {
    "id": 33,
    "translated": "Like, right here. Right here."
  },
  {
    "id": 34,
    "translated": "..."
  },
  {
    "id": 35,
    "translated": "Right here."
  },
  {
    "id": 36,
    "translated": "This is called a torso."
  },
  {
    "id": 37,
    "translated": "\"Reaching for an Unraveling Tomorrow\" also had torsos."
  },
  {
    "id": 38,
    "translated": "It's an illustration where Mizuki is in a space filled with them."
  },
  {
    "id": 39,
    "translated": "\"The torso space usually represents Mizuki's dark feelings,\""
  },
  {
    "id": 40,
    "translated": "\"but this time, they're looking forward after feeling the warmth of family and friends.\""
  },
  {
    "id": 41,
    "translated": "\"It's become a space that shows Mizuki's bright and cheerful feelings, and I'm so happy to see\""
  },
  {
    "id": 42,
    "translated": "\"this change in Mizuki's heart.\""
  },
  {
    "id": 43,
    "translated": "\"I can't thank the staff enough for creating such a wonderful scenario, and the voice actors\""
  },
  {
    "id": 44,
    "translated": "\"for giving the characters such deep and wonderful expressions.\""
  },
  {
    "id": 45,
    "translated": "\"Thank you for always making such great events.\""
  },
  {
    "id": 46,
    "translated": "\"Please take care of yourselves and keep up the good work.\""
  },
  {
    "id": 47,
    "translated": "\"I'll be rooting for you as a fellow Tofu,\" they wrote."
  },
  {
    "id": 48,
    "translated": "Meshi-san, thank you so much."
  },
  {
    "id": 49,
    "translated": "The colors in the illustrations are quite rare for Niigo, or how should I put it..."
  },
  {
    "id": 50,
    "translated": "We've had pale colors before, but seeing Niigo bathed in sunlight..."
  },
  {
    "id": 51,
    "translated": "is rare, probably because they don't go outside much."
  },
  {
    "id": 52,
    "translated": "I thought seeing Niigo during the day was unusual, and this specific art style is quite new."
  },
  {
    "id": 53,
    "translated": "Everyone's cards were great, not just Mizuki's, both before and after training."
  },
  {
    "id": 54,
    "translated": "The artists are truly amazing."
  },
  {
    "id": 55,
    "translated": "I'm really grateful. We also have some comments from the illustration team about the outfits this time,"
  },
  {
    "id": 56,
    "translated": "so I'd like to share those as well."
  },
  {
    "id": 57,
    "translated": "The comment says, \"Pure brightness is quite rare for them, isn't it?\""
  },
  {
    "id": 58,
    "translated": "\"We designed the clothes to show that Mizuki, having been accepted by Niigo, can now be a source of strength\""
  },
  {
    "id": 59,
    "translated": "\"for others who have similar worries or who can't love themselves.\""
  },
  {
    "id": 60,
    "translated": "\"Inspired by the story of Mizuki thinking about their future and wanting a job in fashion,\""
  },
  {
    "id": 61,
    "translated": "\"we chose a simple and clean one-piece dress to represent the future they're starting to envision,\""
  },
  {
    "id": 62,
    "translated": "\"a future that's finally coming into view.\""
  },
  {
    "id": 63,
    "translated": "\"As a special touch, we added the yellow daisy embroidery used in Mizuki's new unit outfit\""
  },
  {
    "id": 64,
    "translated": "\"to convey the message of being yourself.\""
  },
  {
    "id": 65,
    "translated": "\"It's a simple design unique to Mizuki.\""
  },
  {
    "id": 66,
    "translated": "\"To match the song's calm, warm impression and Mizuki's faint expectations for the future,\""
  },
  {
    "id": 67,
    "translated": "\"we used soft and gentle colors,\" they said."
  },
  {
    "id": 68,
    "translated": "It's true, the colors for everyone are very soft overall."
  },
  {
    "id": 69,
    "translated": "That's right. Did everyone notice the daisies? They're there."
  },
  {
    "id": 70,
    "translated": "The daisies are there."
  },
  {
    "id": 71,
    "translated": "I see comments about the daisies now."
  },
  {
    "id": 72,
    "translated": "."
  },
  {
    "id": 73,
    "translated": "."
  },
  {
    "id": 74,
    "translated": "The blue traffic light was also very striking."
  },
  {
    "id": 75,
    "translated": "That's true."
  },
  {
    "id": 76,
    "translated": "Mizuki was born in summer, August 20th... Happy Birthday!"
  },
  {
    "id": 77,
    "translated": "I didn't mean to say it so casually, but Happy Birthday."
  },
  {
    "id": 78,
    "translated": "I feel like Mizuki hasn't had many summer-like illustrations until now."
  },
  {
    "id": 79,
    "translated": "They usually wear long sleeves or clothes that cover their skin."
  }
]