[
  {
    "id": 0,
    "text": "ではランチタイムリクエストのメールをご紹介しましょう。 リエラジオネームみずきさんからいただきました。"
  },
  {
    "id": 1,
    "text": "ほい。"
  },
  {
    "id": 2,
    "text": "ありがとうございます。 スカイリンカーをリクエストします。 この曲の中で一番好きなポイントはなんと言ってもラサビ前のすぐだ、 すぐだ変えてやるよの部分です。 普段低めの声で話すめいちゃんがこの部分では透き通るような高音になっており、 そのギャップと魂からの叫びのような歌声がたまらなく好きです。"
  },
  {
    "id": 3,
    "text": "ありがとうございます。"
  },
  {
    "id": 4,
    "text": "といただきました。"
  },
  {
    "id": 5,
    "text": "ありがとうね。"
  },
  {
    "id": 6,
    "text": "魂を感じますね。"
  },
  {
    "id": 7,
    "text": "すごく熱い楽曲なのでぜひぜひいろんなね、ところ、あの歌声だけじゃなくて後ろの音楽とかに注目して聴いていただけたらなと思います。"
  },
  {
    "id": 8,
    "text": "それではお聞きください。"
  },
  {
    "id": 9,
    "text": "米女命スカイリンカー。"
  },
  {
    "id": 10,
    "text": "欠けたとこばかり気になってるのは"
  },
  {
    "id": 11,
    "text": "完璧な形知っているせいだろう。"
  },
  {
    "id": 12,
    "text": "それでもいい。"
  },
  {
    "id": 13,
    "text": "誰かの迷い終止符不要な神はさには程遠い"
  },
  {
    "id": 14,
    "text": "けど一緒に濡れてくよ、見つかるまで。"
  },
  {
    "id": 15,
    "text": "願いは蒼天の中、この手を望むの連れてく"
  },
  {
    "id": 16,
    "text": "全部、そう全部ふわふわ遮ってやる。"
  },
  {
    "id": 17,
    "text": "例えば運命からも守るよ。"
  },
  {
    "id": 18,
    "text": "ずっと、"
  },
  {
    "id": 19,
    "text": "そうずっと鬱に変わる世界に負けんな、今日も。"
  },
  {
    "id": 20,
    "text": "幾"
  },
  {
    "id": 21,
    "text": "ある立て5ライズ飛んで飛び越えて到着先へ"
  },
  {
    "id": 22,
    "text": "仲間ってやつになってるんだ。"
  },
  {
    "id": 23,
    "text": "自分以外に鍛えと祈る時一点の曇りもない証明するから"
  },
  {
    "id": 24,
    "text": "飛び込め蒼天の中、この手を握るのならやってやる。"
  },
  {
    "id": 25,
    "text": "全部、"
  },
  {
    "id": 26,
    "text": "そう全部弱くて何が悪い?"
  },
  {
    "id": 27,
    "text": "泣きたきゃ泣いてわめこうぜ、かまわない。"
  },
  {
    "id": 28,
    "text": "ずっと、"
  },
  {
    "id": 29,
    "text": "そうずっとどんな君だっていいよ。"
  },
  {
    "id": 30,
    "text": "見せてくれ。"
  },
  {
    "id": 31,
    "text": "ひび割れてしまってますさ、受け止めきってみせるって壊れない。"
  },
  {
    "id": 32,
    "text": "タフな器だよが欲しいのなら澄んだ今がいいのならすぐすぐ変えてやるよ。"
  },
  {
    "id": 33,
    "text": "あの蒼天の中、"
  },
  {
    "id": 34,
    "text": "仰げばこうこうと蒼連れてく"
  },
  {
    "id": 35,
    "text": "全部、"
  },
  {
    "id": 36,
    "text": "そう全部ふわふわ遮ってやる。"
  },
  {
    "id": 37,
    "text": "例えば運命からも守るよ。"
  },
  {
    "id": 38,
    "text": "支えていくここに居場所がある。"
  },
  {
    "id": 39,
    "text": "負けんな、絶対。"
  },
  {
    "id": 40,
    "text": "Love Live! Superstar!!ゆう友情ランチタイム放送局Liella!"
  },
  {
    "id": 41,
    "text": "ラジオ。"
  }
]