[
  {
    "id": 0,
    "translated": "Announcements from Love Live! Superstar!!."
  },
  {
    "id": 1,
    "translated": "First, some music news."
  },
  {
    "id": 2,
    "translated": "On Wednesday, July 8th, the Liella!"
  },
  {
    "id": 3,
    "translated": "Musubu Project mini-album will be released."
  },
  {
    "id": 4,
    "translated": "We'll be releasing five versions: Original, Photo, Team Kids, Team Sports, and Team Green."
  },
  {
    "id": 5,
    "translated": "The Original, Team Kids, Team Sports, and Team Green editions feature new illustrations,"
  },
  {
    "id": 6,
    "translated": "while the Photo edition features brand-new photos of the cast."
  },
  {
    "id": 7,
    "translated": "It'll include 4 songs, including a new group track, plus off-vocal versions for 8 tracks total."
  },
  {
    "id": 8,
    "translated": "First-press bonuses for the Original, Team Kids, Team Sports, and Team Green editions include member stickers."
  },
  {
    "id": 9,
    "translated": "The Photo edition will include a photo-booth style sticker."
  },
  {
    "id": 10,
    "translated": "All versions include a lottery application ticket for the Love Live! Series 15th Anniversary Love Live! Fes."
  },
  {
    "id": 11,
    "translated": "Plus, as a bundle purchase bonus, you'll receive"
  },
  {
    "id": 12,
    "translated": "a Liella! sticker book."
  },
  {
    "id": 13,
    "translated": "Don't forget to pre-order!"
  },
  {
    "id": 14,
    "translated": "To celebrate the release of the Liella!"
  },
  {
    "id": 15,
    "translated": "Musubu Project mini-album, we'll be holding a special handover event."
  },
  {
    "id": 16,
    "translated": "It'll take place over two days: Friday, October 2nd and Friday, October 9th."
  },
  {
    "id": 17,
    "translated": "Customers who pre-order or purchase the mini-album"
  },
  {
    "id": 18,
    "translated": "at participating stores will be entered into a lottery to attend the handover event."
  },
  {
    "id": 19,
    "translated": "The cast members vary by date, so please check the application details before applying."
  },
  {
    "id": 20,
    "translated": "Check the Love Live! Superstar!! official website for more details."
  },
  {
    "id": 21,
    "translated": "Next, news from the Love Live! Series Official Card Game."
  },
  {
    "id": 22,
    "translated": "The Liella!"
  },
  {
    "id": 23,
    "translated": "Start Deck featuring only Liella! members and songs will be released on Saturday, May 30th."
  },
  {
    "id": 24,
    "translated": "This product will include a special rarity \"Secret Serial\" card with a serial number."
  },
  {
    "id": 25,
    "translated": "Each numbered card is a super-luxurious, one-of-a-kind item in the world."
  },
  {
    "id": 26,
    "translated": "The Start Deck has everything you need to play Loveca! right away, so if you haven't tried it yet, grab one and start playing."
  },
  {
    "id": 27,
    "translated": "Stay tuned for the latest updates on the official Love Live! website and official X account."
  },
  {
    "id": 28,
    "translated": "Now for some appearance info."
  },
  {
    "id": 29,
    "translated": "Starting April 1st, Liella!'s"
  },
  {
    "id": 30,
    "translated": "ChuChu Liella!"
  },
  {
    "id": 31,
    "translated": "Season 2 will begin airing on Nippon TV."
  },
  {
    "id": 32,
    "translated": "Haimashin No. 3 will continue as the program MC from Season 1."
  },
  {
    "id": 33,
    "translated": "Catch-up streaming will be available on TVer and Nittele Tada after the broadcast."
  },
  {
    "id": 34,
    "translated": "Be sure to check it out."
  },
  {
    "id": 35,
    "translated": "To commemorate the broadcast, the live concert Love Live! Superstar!! Liella!"
  },
  {
    "id": 36,
    "translated": "no ChuChu Liella!"
  },
  {
    "id": 37,
    "translated": "2026 will be held at LaLa arena TOKYO-BAY on August 1st and 2nd."
  },
  {
    "id": 38,
    "translated": "The second official lottery is open on Ticket Pia until 11:59 PM on Sunday, April 5th."
  },
  {
    "id": 39,
    "translated": "Please check that out as well."
  },
  {
    "id": 40,
    "translated": "For details on all the information shared today, please check the Liella!"
  },
  {
    "id": 41,
    "translated": "official X account and the Love Live! Superstar!! official website."
  }
]