[
  {
    "id": 0,
    "translated": "Everyone loves \"UNIVERSE!!\""
  },
  {
    "id": 1,
    "translated": "I love it so much."
  },
  {
    "id": 2,
    "translated": "It was so fun."
  },
  {
    "id": 3,
    "translated": "It really was."
  },
  {
    "id": 4,
    "translated": "The cheers were so loud, it felt like everyone had been waiting for \"UNIVERSE!!\""
  },
  {
    "id": 5,
    "translated": "I know, right?"
  },
  {
    "id": 6,
    "translated": "Everyone loves that song."
  },
  {
    "id": 7,
    "translated": "We love it too."
  },
  {
    "id": 8,
    "translated": "Yeah."
  },
  {
    "id": 9,
    "translated": "Right."
  },
  {
    "id": 10,
    "translated": "How long has it been since we last played it?"
  },
  {
    "id": 11,
    "translated": "Has it been a while?"
  },
  {
    "id": 12,
    "translated": "It has."
  },
  {
    "id": 13,
    "translated": "That's right."
  },
  {
    "id": 14,
    "translated": "It feels that way, yeah."
  },
  {
    "id": 15,
    "translated": "It really does."
  },
  {
    "id": 16,
    "translated": "I was so moved by everyone singing along during the finale."
  },
  {
    "id": 17,
    "translated": "I even took off my in-ears to listen."
  },
  {
    "id": 18,
    "translated": "We extended the length of the \"woah-woah\" part at the beginning this time."
  },
  {
    "id": 19,
    "translated": "Yeah."
  },
  {
    "id": 20,
    "translated": "Uh-huh."
  },
  {
    "id": 21,
    "translated": "Hearing the voices get louder and louder was such a blast."
  },
  {
    "id": 22,
    "translated": "Yeah."
  },
  {
    "id": 23,
    "translated": "Right?"
  },
  {
    "id": 24,
    "translated": "Yeah."
  },
  {
    "id": 25,
    "translated": "Man, that was great."
  },
  {
    "id": 26,
    "translated": "We got to sing on the sub-stage too."
  },
  {
    "id": 27,
    "translated": "How was it for the 2nd and 3rd gen members?"
  },
  {
    "id": 28,
    "translated": "It was my first time!"
  },
  {
    "id": 29,
    "translated": "It was so fun! We were so close that I could see everyone's faces clearly. Some people were having a blast shouting \"woah-woah,\" while others were sobbing as they sang. Seeing that almost made me tear up too."
  },
  {
    "id": 30,
    "translated": "We were so close."
  },
  {
    "id": 31,
    "translated": "I think it's really amazing."
  },
  {
    "id": 32,
    "translated": "Moments like that remind me how amazing it is that so many people gather to share the same moment and give so much energy to Liella."
  },
  {
    "id": 33,
    "translated": "I'm so grateful we could get closer to everyone. It really means a lot."
  },
  {
    "id": 34,
    "translated": "Yeah."
  },
  {
    "id": 35,
    "translated": "I feel like as we grow up, we have fewer chances to cry or laugh with our whole hearts"
  },
  {
    "id": 36,
    "translated": "compared to when we were kids. So seeing them show us those precious expressions..."
  },
  {
    "id": 37,
    "translated": "it makes me so happy to think they trust us enough to let out all their emotions like that. That's so true."
  },
  {
    "id": 38,
    "translated": "Yeah."
  },
  {
    "id": 39,
    "translated": "I want to do it again."
  },
  {
    "id": 40,
    "translated": "I'm so happy."
  },
  {
    "id": 41,
    "translated": "Me too."
  },
  {
    "id": 42,
    "translated": "Right?"
  },
  {
    "id": 43,
    "translated": "I want to do it."
  },
  {
    "id": 44,
    "translated": "Yeah, I love it."
  },
  {
    "id": 45,
    "translated": "The 7th Live really felt like we were creating the songs together with the audience more than ever before."
  },
  {
    "id": 46,
    "translated": "Let's do the \"woah-woah\" part again!"
  },
  {
    "id": 47,
    "translated": "Yeah."
  },
  {
    "id": 48,
    "translated": "There were so many. So many."
  },
  {
    "id": 49,
    "translated": "We had so much fun too. We've seen so many people saying they had a great time,"
  },
  {
    "id": 50,
    "translated": "um..."
  },
  {
    "id": 51,
    "translated": "but we really had a blast ourselves too."
  },
  {
    "id": 52,
    "translated": "Yeah."
  },
  {
    "id": 53,
    "translated": "Right."
  },
  {
    "id": 54,
    "translated": "On Day 1 of the Aichi performance, people probably expected \"Mirai no Oto ga Kikoeru\" next."
  },
  {
    "id": 55,
    "translated": "Especially those who had been to the Kanagawa shows"
  },
  {
    "id": 56,
    "translated": "and remembered the setlist."
  },
  {
    "id": 57,
    "translated": "They probably thought \"Mirai no Oto ga Kikoeru\" was coming up,"
  },
  {
    "id": 58,
    "translated": "but then I asked the crowd if they could shout \"woah-woah\" again for the next song."
  },
  {
    "id": 59,
    "translated": "That was during Day 1 of the Aichi performance."
  },
  {
    "id": 60,
    "translated": "Then, everyone mistakenly thought \"Open the Gate\" was coming..."
  },
  {
    "id": 61,
    "translated": "Well, it wasn't exactly a mistake."
  },
  {
    "id": 62,
    "translated": "A lot of people thought we were doing \"Open the Gate\" for a third time, so they were all ready to shout, but then \"UNIVERSE!!\" started."
  },
  {
    "id": 63,
    "translated": "Doing the same song three times would've been quite a memory,"
  },
  {
    "id": 64,
    "translated": "and definitely something new!"
  },
  {
    "id": 65,
    "translated": "And then, well..."
  },
  {
    "id": 66,
    "translated": "A \"woah-woah\" song came out of nowhere, which was a surprise."
  },
  {
    "id": 67,
    "translated": "But \"Open the Gate\" also has a lot of call-and-response,"
  },
  {
    "id": 68,
    "translated": "just like you were saying."
  },
  {
    "id": 69,
    "translated": "I'm glad we had so many songs like that this time."
  },
  {
    "id": 70,
    "translated": "Right."
  },
  {
    "id": 71,
    "translated": "It was so fun."
  },
  {
    "id": 72,
    "translated": "I hope we can perform them again. I really do."
  },
  {
    "id": 73,
    "translated": "Yeah."
  },
  {
    "id": 74,
    "translated": "Thank you! And thank you all for sending in so many emails."
  },
  {
    "id": 75,
    "translated": "Thank you!"
  },
  {
    "id": 76,
    "translated": "Thank you very much!"
  },
  {
    "id": 77,
    "translated": "Now, let's introduce a mail for the \"Lunch Time Request\" segment."
  },
  {
    "id": 78,
    "translated": "Okay!"
  },
  {
    "id": 79,
    "translated": "This one is from \"Rieraji Name\" Tetsuo-san."
  }
]