[
  {
    "id": 0,
    "translated": "It was quite intense."
  },
  {
    "id": 1,
    "translated": "I thought Arisa was such a straightforward girl..."
  },
  {
    "id": 2,
    "translated": "Right, Shizuku?"
  },
  {
    "id": 3,
    "translated": "Yeah."
  },
  {
    "id": 4,
    "translated": "The moment Arisa and the others met"
  },
  {
    "id": 5,
    "translated": "the members of Tiade..."
  },
  {
    "id": 6,
    "translated": "Arisa was like, \"I'm going all out,"
  },
  {
    "id": 7,
    "translated": "so you'd better do the same.\""
  },
  {
    "id": 8,
    "translated": "She really puts those feelings into words for you."
  },
  {
    "id": 9,
    "translated": "..."
  },
  {
    "id": 10,
    "translated": "I thought her straightforwardness, always giving it her all,"
  },
  {
    "id": 11,
    "translated": "was..."
  },
  {
    "id": 12,
    "translated": "really cool."
  },
  {
    "id": 13,
    "translated": "But..."
  },
  {
    "id": 14,
    "translated": "Well..."
  },
  {
    "id": 15,
    "translated": "hiding things like that..."
  },
  {
    "id": 16,
    "translated": "The way she went about it"
  },
  {
    "id": 17,
    "translated": "wasn't the best way to handle it."
  },
  {
    "id": 18,
    "translated": "..."
  },
  {
    "id": 19,
    "translated": "So..."
  },
  {
    "id": 20,
    "translated": "..."
  },
  {
    "id": 21,
    "translated": "It's not a bad thing to have those feelings because you want to succeed."
  },
  {
    "id": 22,
    "translated": "I understand that those \"damn it\" feelings come from being serious about it."
  },
  {
    "id": 23,
    "translated": "I have to learn from that. I felt like it wasn't just someone else's problem."
  },
  {
    "id": 24,
    "translated": "If you direct those feelings of jealousy the wrong way,"
  },
  {
    "id": 25,
    "translated": "really bad things can happen. It's difficult to handle those feelings."
  },
  {
    "id": 26,
    "translated": "You just have to find a way to deal with them inside yourself."
  },
  {
    "id": 27,
    "translated": "That \"I won't lose\" feeling can lead to growth"
  },
  {
    "id": 28,
    "translated": "and become the energy to work hard. I want to be that kind of person too."
  },
  {
    "id": 29,
    "translated": "I have those feelings myself sometimes."
  },
  {
    "id": 30,
    "translated": "Like, \"I'm so jealous of her,\" and things like that. Really."
  },
  {
    "id": 31,
    "translated": "Seriously."
  },
  {
    "id": 32,
    "translated": "Every single day, really."
  },
  {
    "id": 33,
    "translated": "I feel it."
  },
  {
    "id": 34,
    "translated": "But on the other hand, Shizuku..."
  },
  {
    "id": 35,
    "translated": "This time, towards the girls who were seriously aiming for the center position..."
  },
  {
    "id": 36,
    "translated": "She said some things she shouldn't have."
  },
  {
    "id": 37,
    "translated": "Of course, she didn't mean any harm."
  },
  {
    "id": 38,
    "translated": "I think everyone who knows Shizuku"
  },
  {
    "id": 39,
    "translated": "understands that about her."
  },
  {
    "id": 40,
    "translated": "It's not that she had bad intentions."
  },
  {
    "id": 41,
    "translated": "Shizuku was just so overwhelmed at the time,"
  },
  {
    "id": 42,
    "translated": "and she could only see what was right in front of her. That's why she blurted out that someone else might be better for the center."
  },
  {
    "id": 43,
    "translated": "It just came out."
  },
  {
    "id": 44,
    "translated": "I understand that feeling too."
  },
  {
    "id": 45,
    "translated": "The pressure of being the center is insane."
  },
  {
    "id": 46,
    "translated": "Between the expectations and her persona... Shizuku wasn't being her true self."
  },
  {
    "id": 47,
    "translated": "She had a character she maintained thanks to everyone, which made it even harder."
  },
  {
    "id": 48,
    "translated": "That was part of it too."
  },
  {
    "id": 49,
    "translated": "Truly."
  }
]